Metadata-Version: 2.1
Name: loft
Version: 0.0.3
Summary: A fresh package for training & validating & evaling under data-parrallel distribution. This package is avaliable for torch and paddle deep-learning frameworks.
Home-page: https://github.com/EagerSun/loft
Author: Eager Sun
Author-email: eagersyg@gmail.com
License: MIT
Keywords: loft,paddle,torch
Classifier: Development Status :: 5 - Production/Stable
Classifier: Intended Audience :: Science/Research
Classifier: License :: OSI Approved :: MIT License
Classifier: Operating System :: POSIX :: Linux
Classifier: Programming Language :: Python :: 3.6
Classifier: Programming Language :: Python :: 3.7
Classifier: Programming Language :: Python :: 3.8
Classifier: Programming Language :: Python :: 3.9
Classifier: Programming Language :: Python :: 3.10
Requires-Python: >=3.6
License-File: LICENSE
